{
  "candidates": [
    {
      "auth_required": false,
      "confidence": "medium",
      "id": "community-sn-49-data-artifact-tournament-api-nepher-ai",
      "kind": "data-artifact",
      "name": "Nepher Robotics community data-artifact",
      "netuid": 49,
      "provider": "nepher-robotics",
      "public_safe": true,
      "rate_limit_notes": "",
      "review_notes": "Community-submitted public interface candidate.",
      "schema_version": 1,
      "source_tier": "community-docs",
      "source_type": "community-pr-intake",
      "source_url": "https://tournament-api.nepher.ai/openapi.json",
      "source_urls": ["https://tournament-api.nepher.ai/openapi.json"],
      "state": "schema-valid",
      "url": "https://tournament-api.nepher.ai/api/v1/scores/leaderboard/active"
    }
  ],
  "schema_version": 1,
  "submission": {
    "submitted_by": "kiannidev",
    "submitted_by_url": "https://github.com/kiannidev"
  }
}
